mcp_sqlite/server.py
mcp_sqlite-0.3.2.dist-info/licenses/LICENSE
mcp_sqlite-0.3.2.dist-info/METADATA
mcp_sqlite-0.3.2.dist-info/WHEEL
mcp_sqlite-0.3.2.dist-info/entry_points.txt
mcp_sqlite-0.3.2.dist-info/top_level.txt
mcp_sqlite-0.3.2.dist-info/RECORD
