Metadata-Version: 2.4
Name: mcp-sqlite
Version: 0.3.2
Summary: MCP server for SQLite files. Supports Datasette-compatible metadata!
Project-URL: Homepage, https://github.com/panasenco/mcp-sqlite
Project-URL: Issues, https://github.com/panasenco/mcp-sqlite/issues
Project-URL: Repository, https://github.com/panasenco/mcp-sqlite.git
Requires-Python: >=3.12
License-File: LICENSE
Requires-Dist: aiosqlite>=0.21.0
Requires-Dist: anyio>=4.9.0
Requires-Dist: mcp>=1.9.2
Requires-Dist: pydantic>=2.11.5
Requires-Dist: pyyaml>=6.0.2
Dynamic: license-file
